<?xml version="1.0" encoding="UTF-8"?><sv:node xmlns:sv="http://www.jcp.org/jcr/sv/1.0" xmlns:xsi="http://www.w3.org/2001/XMLSchema-instance" sv:name="News_7"><sv:property sv:name="jcr:primaryType" sv:type="Name"><sv:value>news</sv:value></sv:property><sv:property sv:name="jcr:uuid" sv:type="String"><sv:value>08e36302-7103-4192-b66a-971f032d8a57</sv:value></sv:property><sv:property sv:name="category" sv:type="String"><sv:value>events</sv:value></sv:property><sv:property sv:name="ends" sv:type="Date"><sv:value>2024-10-06T20:00:00.000+01:00</sv:value></sv:property><sv:property sv:name="imageLink" sv:type="String"><sv:value>jcr:c6fc325b-5d14-453e-a9f7-e3f97bd23f14</sv:value></sv:property><sv:property sv:name="location" sv:type="String"><sv:value>Auditorio Alfredo Kraus</sv:value></sv:property><sv:property sv:name="message" sv:type="String"><sv:value>&lt;p&gt;Canary Islands top business innovation event for startups, investors, &amp;amp; national VCs.&lt;/p&gt;
</sv:value></sv:property><sv:property sv:name="mgnl:activationStatus" sv:type="Boolean"><sv:value>true</sv:value></sv:property><sv:property sv:name="mgnl:created" sv:type="Date"><sv:value>2024-03-31T20:52:37.673+01:00</sv:value></sv:property><sv:property sv:name="mgnl:createdBy" sv:type="String"><sv:value>superuser</sv:value></sv:property><sv:property sv:name="mgnl:lastActivated" sv:type="Date"><sv:value>2024-03-31T20:55:13.207+01:00</sv:value></sv:property><sv:property sv:name="mgnl:lastActivatedBy" sv:type="String"><sv:value>superuser</sv:value></sv:property><sv:property sv:name="mgnl:lastModified" sv:type="Date"><sv:value>2024-03-31T23:32:56.803+01:00</sv:value></sv:property><sv:property sv:name="mgnl:lastModifiedBy" sv:type="String"><sv:value>superuser</sv:value></sv:property><sv:property sv:name="name" sv:type="String"><sv:value>News_7</sv:value></sv:property><sv:property sv:name="starts" sv:type="Date"><sv:value>2024-10-04T10:00:00.000+01:00</sv:value></sv:property><sv:property sv:name="title" sv:type="String"><sv:value>Canary Islands innovates</sv:value></sv:property><sv:node sv:name="contacts"><sv:property sv:name="jcr:primaryType" sv:type="Name"><sv:value>mgnl:contentNode</sv:value></sv:property><sv:property sv:name="jcr:uuid" sv:type="String"><sv:value>4d57be22-d5a5-4d48-a88f-0a18236c5c09</sv:value></sv:property><sv:property sv:name="mgnl:activationStatus" sv:type="Boolean"><sv:value>true</sv:value></sv:property><sv:property sv:name="mgnl:created" sv:type="Date"><sv:value>2024-03-31T20:52:37.696+01:00</sv:value></sv:property><sv:property sv:name="mgnl:createdBy" sv:type="String"><sv:value>superuser</sv:value></sv:property><sv:property sv:name="mgnl:lastActivated" sv:type="Date"><sv:value>2024-03-31T20:55:13.209+01:00</sv:value></sv:property><sv:property sv:name="mgnl:lastActivatedBy" sv:type="String"><sv:value>superuser</sv:value></sv:property><sv:property sv:name="mgnl:lastModified" sv:type="Date"><sv:value>2024-03-31T23:32:56.798+01:00</sv:value></sv:property><sv:property sv:name="mgnl:lastModifiedBy" sv:type="String"><sv:value>superuser</sv:value></sv:property><sv:node sv:name="0"><sv:property sv:name="jcr:primaryType" sv:type="Name"><sv:value>contact</sv:value></sv:property><sv:property sv:name="jcr:uuid" sv:type="String"><sv:value>94ec3e86-9f0b-49fd-aa74-7187b6ac74d3</sv:value></sv:property><sv:property sv:name="email" sv:type="String"><sv:value>contacto@sercotel.com</sv:value></sv:property><sv:property sv:name="familyName" sv:type="String"><sv:value>Cabrera</sv:value></sv:property><sv:property sv:name="firstName" sv:type="String"><sv:value>Elena</sv:value></sv:property><sv:property sv:name="mgnl:activationStatus" sv:type="Boolean"><sv:value>true</sv:value></sv:property><sv:property sv:name="mgnl:created" sv:type="Date"><sv:value>2024-03-31T20:52:37.700+01:00</sv:value></sv:property><sv:property sv:name="mgnl:createdBy" sv:type="String"><sv:value>superuser</sv:value></sv:property><sv:property sv:name="mgnl:lastActivated" sv:type="Date"><sv:value>2024-03-31T20:55:13.210+01:00</sv:value></sv:property><sv:property sv:name="mgnl:lastActivatedBy" sv:type="String"><sv:value>superuser</sv:value></sv:property><sv:property sv:name="mgnl:lastModified" sv:type="Date"><sv:value>2024-03-31T23:32:56.798+01:00</sv:value></sv:property><sv:property sv:name="mgnl:lastModifiedBy" sv:type="String"><sv:value>superuser</sv:value></sv:property><sv:property sv:name="mobileNumber" sv:type="String"><sv:value>34</sv:value></sv:property><sv:property sv:name="phoneNumber" sv:type="String"><sv:value>928 49 17 70</sv:value></sv:property></sv:node></sv:node><sv:node sv:name="addresses"><sv:property sv:name="jcr:primaryType" sv:type="Name"><sv:value>mgnl:contentNode</sv:value></sv:property><sv:property sv:name="jcr:uuid" sv:type="String"><sv:value>3f5210b1-96d1-4cb6-af20-b36818f6e602</sv:value></sv:property><sv:property sv:name="mgnl:activationStatus" sv:type="Boolean"><sv:value>true</sv:value></sv:property><sv:property sv:name="mgnl:created" sv:type="Date"><sv:value>2024-03-31T20:52:37.705+01:00</sv:value></sv:property><sv:property sv:name="mgnl:createdBy" sv:type="String"><sv:value>superuser</sv:value></sv:property><sv:property sv:name="mgnl:lastActivated" sv:type="Date"><sv:value>2024-03-31T20:55:13.211+01:00</sv:value></sv:property><sv:property sv:name="mgnl:lastActivatedBy" sv:type="String"><sv:value>superuser</sv:value></sv:property><sv:property sv:name="mgnl:lastModified" sv:type="Date"><sv:value>2024-03-31T23:32:56.803+01:00</sv:value></sv:property><sv:property sv:name="mgnl:lastModifiedBy" sv:type="String"><sv:value>superuser</sv:value></sv:property><sv:node sv:name="0"><sv:property sv:name="jcr:primaryType" sv:type="Name"><sv:value>address</sv:value></sv:property><sv:property sv:name="jcr:uuid" sv:type="String"><sv:value>e6b6a3b8-6695-40b1-a1f2-7b1cd60006b1</sv:value></sv:property><sv:property sv:name="country" sv:type="String"><sv:value>Spain</sv:value></sv:property><sv:property sv:name="mgnl:activationStatus" sv:type="Boolean"><sv:value>true</sv:value></sv:property><sv:property sv:name="mgnl:created" sv:type="Date"><sv:value>2024-03-31T20:52:37.706+01:00</sv:value></sv:property><sv:property sv:name="mgnl:createdBy" sv:type="String"><sv:value>superuser</sv:value></sv:property><sv:property sv:name="mgnl:lastActivated" sv:type="Date"><sv:value>2024-03-31T20:55:13.214+01:00</sv:value></sv:property><sv:property sv:name="mgnl:lastActivatedBy" sv:type="String"><sv:value>superuser</sv:value></sv:property><sv:property sv:name="mgnl:lastModified" sv:type="Date"><sv:value>2024-03-31T23:32:56.803+01:00</sv:value></sv:property><sv:property sv:name="mgnl:lastModifiedBy" sv:type="String"><sv:value>superuser</sv:value></sv:property><sv:property sv:name="postalCode" sv:type="String"><sv:value>35010</sv:value></sv:property><sv:property sv:name="province" sv:type="String"><sv:value>Las Palmas</sv:value></sv:property><sv:property sv:name="street" sv:type="String"><sv:value>Avda, Ctra. del Rincón</sv:value></sv:property></sv:node></sv:node></sv:node>